{
  "background": {
    "primary": "#FFFFFF",
    "button": {
      "default": "#eaf3ff",
      "default-hover": "#d4e8fe",
      "default-active": "#aad1fd",
      "danger": "#fddcdb",
      "danger-hover": "#fbb9b7",
      "danger-active": "#fa9693",
      "success": "#def3e9",
      "success-hover": "#bde7d2",
      "success-active": "#9bdabc",
      "brand": "#2A8BFB",
      "brand-hover": "#226fc9",
      "brand-active": "#195397",
      "link": "#FFFFFF00",
      "link-hover": "#FFFFFF00",
      "link-active": "#eaf3ff"
    }
  },
  "text": {
    "primary": "#002E61",
    "secondary": "#FFFFFF",
    "button": {
      "danger": "#94302d",
      "link": "#2A8BFB",
      "link-hover": "#226fc9"
    }
  },
  "border": {
    "wcag": "#E3679F"
  }
}